optuna_worker/__about__.py
optuna_worker/__init__.py
optuna_worker/cli.py
optuna_worker/model.py
optuna_worker/worker.py
optuna_worker-0.1.0.dist-info/METADATA
optuna_worker-0.1.0.dist-info/WHEEL
optuna_worker-0.1.0.dist-info/entry_points.txt
optuna_worker-0.1.0.dist-info/licenses/LICENSE.txt
optuna_worker-0.1.0.dist-info/RECORD
