Metadata-Version: 2.1
Name: optuna-worker
Version: 0.1.0
Summary: Optuna Worker
Project-URL: Documentation, https://github.com/jooong/optuna-worker#readme
Project-URL: Issues, https://github.com/jooong/optuna-worker/issues
Project-URL: Source, https://github.com/jooong/optuna-worker
Author-email: jooong <joong937@gmail.com>
License-Expression: MIT
License-File: LICENSE.txt
Classifier: Development Status :: 4 - Beta
Classifier: Programming Language :: Python
Classifier: Programming Language :: Python :: 3.8
Classifier: Programming Language :: Python :: 3.9
Classifier: Programming Language :: Python :: 3.10
Classifier: Programming Language :: Python :: 3.11
Classifier: Programming Language :: Python :: Implementation :: CPython
Classifier: Programming Language :: Python :: Implementation :: PyPy
Requires-Python: >=3.8
Requires-Dist: click
Requires-Dist: loguru
Requires-Dist: optuna
Requires-Dist: pydantic
Requires-Dist: pyyaml
